cognite/cdffs/__init__.py
cognite/cdffs/az_upload_strategy.py
cognite/cdffs/credentials.py
cognite/cdffs/file_handler.py
cognite/cdffs/gcp_upload_strategy.py
cognite/cdffs/memory_upload_strategy.py
cognite/cdffs/spec.py
cognite/cdffs/upload_strategy.py
vendor/__init__.py
vendor/pydantic/__init__.py
vendor/pydantic/annotated_types.py
vendor/pydantic/class_validators.py
vendor/pydantic/color.py
vendor/pydantic/config.py
vendor/pydantic/dataclasses.py
vendor/pydantic/datetime_parse.py
vendor/pydantic/env_settings.py
vendor/pydantic/error_wrappers.py
vendor/pydantic/errors.py
vendor/pydantic/fields.py
vendor/pydantic/json.py
vendor/pydantic/main.py
vendor/pydantic/networks.py
vendor/pydantic/parse.py
vendor/pydantic/schema.py
vendor/pydantic/types.py
vendor/pydantic/typing.py
vendor/pydantic/utils.py
vendor/pydantic/validators.py
vendor/pydantic/version.py
cognite_cdffs-0.3.8.dist-info/WHEEL
cognite_cdffs-0.3.8.dist-info/METADATA
cognite_cdffs-0.3.8.dist-info/RECORD
