Metadata-Version: 2.1
Name: cognite-cdffs
Version: 0.3.8
Summary: File System Interface for CDF Files
License: Apache-2.0
Author: Infant Alex
Author-email: infant.alex@cognite.com
Requires-Python: >=3.9.10,<3.13
Classifier: License :: OSI Approved :: Apache Software License
Classifier: Programming Language :: Python :: 3
Classifier: Programming Language :: Python :: 3.10
Classifier: Programming Language :: Python :: 3.11
Requires-Dist: cognite-sdk (>=7.32.0,<8.0.0)
Requires-Dist: fsspec (>=2024.3.1,<2025.0.0)
Requires-Dist: python-dotenv (>=1.0.1,<2.0.0)
Requires-Dist: requests (>=2.31.0,<3.0.0)
Requires-Dist: tenacity (>=9.0.0,<10.0.0)
Requires-Dist: twine (>=5.0.0,<6.0.0)
